civic2clinvar/__init__.py
civic2clinvar/c2c.py
civic2clinvar/cli.py
civic2clinvar/definitions.py
civic2clinvar-0.0.1a4.dist-info/METADATA
civic2clinvar-0.0.1a4.dist-info/RECORD
civic2clinvar-0.0.1a4.dist-info/WHEEL
civic2clinvar-0.0.1a4.dist-info/entry_points.txt
civic2clinvar-0.0.1a4.dist-info/top_level.txt
